postmarker/__init__.py
postmarker/core.py
postmarker/exceptions.py
postmarker/logging.py
postmarker/pytest.py
postmarker/tornado.py
postmarker/utils.py
postmarker/django/__init__.py
postmarker/django/backend.py
postmarker/django/signals.py
postmarker/models/__init__.py
postmarker/models/base.py
postmarker/models/bounces.py
postmarker/models/domains.py
postmarker/models/emails.py
postmarker/models/messages.py
postmarker/models/senders.py
postmarker/models/server.py
postmarker/models/stats.py
postmarker/models/status.py
postmarker/models/templates.py
postmarker/models/triggers.py
postmarker-1.0.dist-info/LICENSE
postmarker-1.0.dist-info/METADATA
postmarker-1.0.dist-info/WHEEL
postmarker-1.0.dist-info/entry_points.txt
postmarker-1.0.dist-info/top_level.txt
postmarker-1.0.dist-info/RECORD
